[
  {
    "id": 1,
    "name": "张伟",
    "gender": "男",
    "age": 28,
    "degree": "本科",
    "years": 5,
    "current": "中建三局（造价工程师）",
    "salary": "18K-22K",
    "match": 92,
    "tags": ["经验吻合", "地域匹配", "薪资匹配"],
    "reason": "候选人具备土建造价经验，熟悉成本测算与项目结算流程。",
    "avatar": "张",
    "filter_tags": ["土建造价", "上海", "本科", "5 年以上"],
    "keywords": ["张伟", "造价工程师", "广联达", "成本控制", "土建造价", "安装造价师"],
    "target_roles": ["土建造价师", "造价工程师"],
    "city": "上海"
  },
  {
    "id": 2,
    "name": "李娜",
    "gender": "女",
    "age": 29,
    "degree": "本科",
    "years": 6,
    "current": "智谱科技（后端开发工程师）",
    "salary": "28K-35K",
    "match": 95,
    "tags": ["技术栈吻合", "经验充足", "城市匹配"],
    "reason": "候选人长期负责 Java 微服务开发，具备缓存、消息队列与接口性能优化经验。",
    "avatar": "李",
    "filter_tags": ["后端开发", "上海", "本科", "5 年以上"],
    "keywords": ["李娜", "java", "spring cloud", "redis", "微服务"],
    "target_roles": ["Java 后端工程师", "微服务架构师"],
    "city": "上海"
  },
  {
    "id": 3,
    "name": "王强",
    "gender": "男",
    "age": 31,
    "degree": "硕士",
    "years": 7,
    "current": "云舟数据（数据产品经理）",
    "salary": "26K-34K",
    "match": 90,
    "tags": ["岗位方向匹配", "数据经验", "沟通能力"],
    "reason": "候选人负责过指标体系和用户画像产品，能够衔接业务、数据和研发团队。",
    "avatar": "王",
    "filter_tags": ["数据产品", "上海", "硕士", "5 年以上"],
    "keywords": ["王强", "指标体系", "用户画像", "数据中台", "需求分析"],
    "target_roles": ["数据产品经理", "数据中台产品经理"],
    "city": "上海"
  },
  {
    "id": 4,
    "name": "赵敏",
    "gender": "女",
    "age": 26,
    "degree": "本科",
    "years": 4,
    "current": "灵犀科技（前端工程师）",
    "salary": "20K-28K",
    "match": 88,
    "tags": ["前端经验", "可视化经验", "学习能力"],
    "reason": "候选人熟悉 React 与 TypeScript，参与过多套数据看板和组件库建设。",
    "avatar": "赵",
    "filter_tags": ["前端开发", "杭州", "本科", "3-5 年"],
    "keywords": ["赵敏", "react", "typescript", "echarts", "可视化"],
    "target_roles": ["前端可视化工程师", "React 前端工程师"],
    "city": "杭州"
  },
  {
    "id": 5,
    "name": "陈晨",
    "gender": "男",
    "age": 32,
    "degree": "硕士",
    "years": 8,
    "current": "星河智能（算法工程师）",
    "salary": "35K-45K",
    "match": 93,
    "tags": ["算法能力", "平台经验", "模型评估"],
    "reason": "候选人负责过推荐模型训练和推理平台，能够推进模型效果评估和工程部署。",
    "avatar": "陈",
    "filter_tags": ["算法工程", "北京", "硕士", "5 年以上"],
    "keywords": ["陈晨", "机器学习", "推荐系统", "pytorch", "向量检索"],
    "target_roles": ["AI 平台算法工程师", "推荐算法工程师"],
    "city": "北京"
  },
  {
    "id": 6,
    "name": "刘洋",
    "gender": "男",
    "age": 25,
    "degree": "本科",
    "years": 3,
    "current": "明澈咨询（数据分析师）",
    "salary": "15K-20K",
    "match": 86,
    "tags": ["分析基础", "业务理解", "成本可控"],
    "reason": "候选人熟悉 SQL 与 BI 报表，能够独立支持经营分析和渠道转化复盘。",
    "avatar": "刘",
    "filter_tags": ["数据分析", "成都", "本科", "3-5 年"],
    "keywords": ["刘洋", "sql", "bi", "经营分析", "渠道分析"],
    "target_roles": ["商业数据分析师", "数据分析师"],
    "city": "成都"
  }
]
